CHANGES.txt
COPYRIGHT.txt
LICENSE.txt
README.txt
TODO.txt
ez_setup.py
setup.py
repoze/__init__.py
repoze.monty.egg-info/PKG-INFO
repoze.monty.egg-info/SOURCES.txt
repoze.monty.egg-info/dependency_links.txt
repoze.monty.egg-info/entry_points.txt
repoze.monty.egg-info/namespace_packages.txt
repoze.monty.egg-info/not-zip-safe
repoze.monty.egg-info/top_level.txt
repoze/monty/__init__.py
repoze/monty/tests.py